Metadata-Version: 1.0
Name: standard-statistical-distributions-gauss
Version: 0.1
Summary: Gaussian and Binomial distributions
Home-page: UNKNOWN
Author: Greg Jones
Author-email: UNKNOWN
License: UNKNOWN
Platform: UNKNOWN
